{"summary":{"avgVariancePct":4.73,"medianVariancePct":5.5,"count":997},"bySection":[{"name":"ACCESS/SPONSORSHIP FEES","avgVariancePct":5.44,"totalOverUnder":1623536.35,"eventCount":713},{"name":"PLANNING & ADMINISTRATION","avgVariancePct":5.39,"totalOverUnder":1558017.9,"eventCount":710},{"name":"ONSITE LABOR ACTIVITY","avgVariancePct":6,"totalOverUnder":1534340.1,"eventCount":595},{"name":"LOGISTICS EXPENSES","avgVariancePct":4.39,"totalOverUnder":1337189.85,"eventCount":607},{"name":"TRAVEL EXPENSES","avgVariancePct":4.45,"totalOverUnder":954113.82,"eventCount":671},{"name":"PRODUCTION EXPENSES","avgVariancePct":3.44,"totalOverUnder":807220.62,"eventCount":630},{"name":"CREATIVE COSTS","avgVariancePct":4.34,"totalOverUnder":724409.62,"eventCount":599}],"byClient":[{"name":"Kia","avgVariancePct":6.91,"totalOverUnder":541859.52,"eventCount":41},{"name":"Ford","avgVariancePct":5.83,"totalOverUnder":453893.23,"eventCount":44},{"name":"Infiniti","avgVariancePct":5.56,"totalOverUnder":427960.31,"eventCount":46},{"name":"Nissan","avgVariancePct":6.99,"totalOverUnder":378986.32,"eventCount":39},{"name":"Chrysler","avgVariancePct":4.66,"totalOverUnder":372292.4,"eventCount":37},{"name":"Jaguar","avgVariancePct":6.77,"totalOverUnder":371577.37,"eventCount":34},{"name":"BMW","avgVariancePct":7.17,"totalOverUnder":359088.74,"eventCount":33},{"name":"Volkswagen","avgVariancePct":7.46,"totalOverUnder":348929.09,"eventCount":31},{"name":"Hyundai","avgVariancePct":4.85,"totalOverUnder":329798.43,"eventCount":34},{"name":"Rivian","avgVariancePct":4.85,"totalOverUnder":319978.48,"eventCount":30},{"name":"Audi","avgVariancePct":4.46,"totalOverUnder":312610.16,"eventCount":33},{"name":"Cadillac","avgVariancePct":2.72,"totalOverUnder":311312.92,"eventCount":45},{"name":"Porsche","avgVariancePct":4.74,"totalOverUnder":310975.22,"eventCount":30},{"name":"Lincoln","avgVariancePct":4.06,"totalOverUnder":308726.58,"eventCount":39},{"name":"Honda","avgVariancePct":5.17,"totalOverUnder":305497.44,"eventCount":32},{"name":"Lucid","avgVariancePct":4.88,"totalOverUnder":281186.78,"eventCount":34},{"name":"Mazda","avgVariancePct":6.14,"totalOverUnder":277708.87,"eventCount":28},{"name":"Dodge","avgVariancePct":5.09,"totalOverUnder":272723.9,"eventCount":31},{"name":"Subaru","avgVariancePct":3.4,"totalOverUnder":251545.43,"eventCount":39},{"name":"Toyota","avgVariancePct":5.69,"totalOverUnder":239278.82,"eventCount":28},{"name":"Lexus","avgVariancePct":3.05,"totalOverUnder":236705.14,"eventCount":26},{"name":"Genesis","avgVariancePct":3.22,"totalOverUnder":205500.75,"eventCount":33},{"name":"Volvo","avgVariancePct":6.67,"totalOverUnder":190446.19,"eventCount":24},{"name":"Land Rover","avgVariancePct":3.73,"totalOverUnder":188432.54,"eventCount":31},{"name":"Acura","avgVariancePct":1.97,"totalOverUnder":186462.1,"eventCount":33},{"name":"Mercedes-Benz","avgVariancePct":4.31,"totalOverUnder":174663.58,"eventCount":33},{"name":"Jeep","avgVariancePct":4.59,"totalOverUnder":174234.46,"eventCount":25},{"name":"Ram","avgVariancePct":1.77,"totalOverUnder":164981.28,"eventCount":33},{"name":"Mini","avgVariancePct":2.89,"totalOverUnder":164801.96,"eventCount":29},{"name":"Chevrolet","avgVariancePct":1.01,"totalOverUnder":76670.25,"eventCount":22}],"byOffice":[{"name":"Los Angeles","avgVariancePct":5.67,"totalOverUnder":805964.47,"eventCount":69},{"name":"Atlanta","avgVariancePct":6.24,"totalOverUnder":767696.18,"eventCount":70},{"name":"Boston","avgVariancePct":7.24,"totalOverUnder":730071.65,"eventCount":54},{"name":"Seattle","avgVariancePct":5.23,"totalOverUnder":686692.37,"eventCount":60},{"name":"Charlotte","avgVariancePct":3.74,"totalOverUnder":664546.47,"eventCount":78},{"name":"Detroit","avgVariancePct":5.96,"totalOverUnder":659565.13,"eventCount":63},{"name":"Miami","avgVariancePct":4.65,"totalOverUnder":583469.53,"eventCount":70},{"name":"Denver","avgVariancePct":4.7,"totalOverUnder":547154.28,"eventCount":68},{"name":"Chicago","avgVariancePct":4.07,"totalOverUnder":528249.68,"eventCount":62},{"name":"Portland","avgVariancePct":3.48,"totalOverUnder":520877.85,"eventCount":69},{"name":"Phoenix","avgVariancePct":4.08,"totalOverUnder":475221.62,"eventCount":75},{"name":"Dallas","avgVariancePct":5.03,"totalOverUnder":455005.2,"eventCount":72},{"name":"Nashville","avgVariancePct":4.83,"totalOverUnder":392222.49,"eventCount":50},{"name":"New York","avgVariancePct":4.21,"totalOverUnder":383702.21,"eventCount":67},{"name":"San Francisco","avgVariancePct":2.72,"totalOverUnder":338389.13,"eventCount":70}],"events":[{"event_name":"Genesis Regional Tour","client":"Genesis","lead_office":"Charlotte","grandTotalBid":310825.24,"grandTotalActual":391076.81,"variance":80251.57,"variancePct":25.82},{"event_name":"Rivian VIP Experience","client":"Rivian","lead_office":"Chicago","grandTotalBid":286335.19,"grandTotalActual":359575.22,"variance":73240.03,"variancePct":25.58},{"event_name":"Lincoln Brand Activation","client":"Lincoln","lead_office":"Boston","grandTotalBid":260775.32,"grandTotalActual":331001.94,"variance":70226.62,"variancePct":26.93},{"event_name":"Jeep VIP Experience","client":"Jeep","lead_office":"Detroit","grandTotalBid":266843.43,"grandTotalActual":333036.32,"variance":66192.89,"variancePct":24.81},{"event_name":"Subaru Dealer Meeting","client":"Subaru","lead_office":"Nashville","grandTotalBid":299258.73,"grandTotalActual":365285.5,"variance":66026.77,"variancePct":22.06},{"event_name":"Lucid Test Drive Program","client":"Lucid","lead_office":"Chicago","grandTotalBid":219307.61,"grandTotalActual":284107.67,"variance":64800.06,"variancePct":29.55},{"event_name":"Cadillac Auto Show 2023","client":"Cadillac","lead_office":"Charlotte","grandTotalBid":370164.23,"grandTotalActual":433035.92,"variance":62871.69,"variancePct":16.98},{"event_name":"Lexus VIP Experience","client":"Lexus","lead_office":"Portland","grandTotalBid":329264.8,"grandTotalActual":391910.57,"variance":62645.77,"variancePct":19.03},{"event_name":"Cadillac Drive Experience","client":"Cadillac","lead_office":"Denver","grandTotalBid":285713.17,"grandTotalActual":347636.78,"variance":61923.61,"variancePct":21.67},{"event_name":"Lexus Test Drive Program","client":"Lexus","lead_office":"Seattle","grandTotalBid":230706.35,"grandTotalActual":291764.13,"variance":61057.78,"variancePct":26.47},{"event_name":"Lexus Auto Show 2025","client":"Lexus","lead_office":"Portland","grandTotalBid":253397.51,"grandTotalActual":313677.47,"variance":60279.96,"variancePct":23.79},{"event_name":"Audi Dealer Meeting","client":"Audi","lead_office":"Atlanta","grandTotalBid":334852.53,"grandTotalActual":394846.28,"variance":59993.75,"variancePct":17.92},{"event_name":"BMW Auto Show 2020","client":"BMW","lead_office":"Detroit","grandTotalBid":177800.42,"grandTotalActual":236455.15,"variance":58654.73,"variancePct":32.99},{"event_name":"Porsche Auto Show 2023","client":"Porsche","lead_office":"Atlanta","grandTotalBid":412818.67,"grandTotalActual":470134.95,"variance":57316.28,"variancePct":13.88},{"event_name":"Volkswagen Regional Tour","client":"Volkswagen","lead_office":"Boston","grandTotalBid":194066.47,"grandTotalActual":251380.62,"variance":57314.15,"variancePct":29.53},{"event_name":"Porsche Brand Activation","client":"Porsche","lead_office":"New York","grandTotalBid":291983.75,"grandTotalActual":348715.35,"variance":56731.6,"variancePct":19.43},{"event_name":"Kia Brand Activation","client":"Kia","lead_office":"Seattle","grandTotalBid":269571.07,"grandTotalActual":325774.14,"variance":56203.07,"variancePct":20.85},{"event_name":"Hyundai Brand Activation","client":"Hyundai","lead_office":"New York","grandTotalBid":189254.35,"grandTotalActual":244606.25,"variance":55351.9,"variancePct":29.25},{"event_name":"Genesis Launch Event","client":"Genesis","lead_office":"Charlotte","grandTotalBid":318030.14,"grandTotalActual":370968.81,"variance":52938.67,"variancePct":16.65},{"event_name":"Toyota Test Drive Program","client":"Toyota","lead_office":"Detroit","grandTotalBid":223367.59,"grandTotalActual":276256.9,"variance":52889.31,"variancePct":23.68},{"event_name":"Lincoln Regional Tour","client":"Lincoln","lead_office":"Boston","grandTotalBid":229135.67,"grandTotalActual":281464.57,"variance":52328.9,"variancePct":22.84},{"event_name":"Kia VIP Experience","client":"Kia","lead_office":"Dallas","grandTotalBid":288789.89,"grandTotalActual":340447.17,"variance":51657.28,"variancePct":17.89},{"event_name":"Genesis Brand Activation","client":"Genesis","lead_office":"Miami","grandTotalBid":389242.89,"grandTotalActual":440882.81,"variance":51639.92,"variancePct":13.27},{"event_name":"Toyota Auto Show 2022","client":"Toyota","lead_office":"Dallas","grandTotalBid":342911.86,"grandTotalActual":292386.16,"variance":-50525.7,"variancePct":-14.73},{"event_name":"Porsche Brand Activation","client":"Porsche","lead_office":"Atlanta","grandTotalBid":185114.56,"grandTotalActual":234650.56,"variance":49536,"variancePct":26.76},{"event_name":"Ram Dealer Meeting","client":"Ram","lead_office":"Portland","grandTotalBid":287818.99,"grandTotalActual":239135.46,"variance":-48683.53,"variancePct":-16.91},{"event_name":"Chevrolet Brand Activation","client":"Chevrolet","lead_office":"Phoenix","grandTotalBid":205918.87,"grandTotalActual":254550.2,"variance":48631.33,"variancePct":23.62},{"event_name":"Ford VIP Experience","client":"Ford","lead_office":"Denver","grandTotalBid":347756.61,"grandTotalActual":396001.33,"variance":48244.72,"variancePct":13.87},{"event_name":"Acura Drive Experience","client":"Acura","lead_office":"Denver","grandTotalBid":254938.34,"grandTotalActual":303161.23,"variance":48222.89,"variancePct":18.92},{"event_name":"Infiniti Launch Event","client":"Infiniti","lead_office":"Portland","grandTotalBid":180948.74,"grandTotalActual":229071.56,"variance":48122.82,"variancePct":26.59},{"event_name":"Infiniti Launch Event","client":"Infiniti","lead_office":"Boston","grandTotalBid":264303.22,"grandTotalActual":312143.17,"variance":47839.95,"variancePct":18.1},{"event_name":"Volvo Test Drive Program","client":"Volvo","lead_office":"Nashville","grandTotalBid":365820.92,"grandTotalActual":318127.77,"variance":-47693.15,"variancePct":-13.04},{"event_name":"Kia Auto Show 2018","client":"Kia","lead_office":"Seattle","grandTotalBid":181048.3,"grandTotalActual":228732.07,"variance":47683.77,"variancePct":26.34},{"event_name":"Chrysler Launch Event","client":"Chrysler","lead_office":"Los Angeles","grandTotalBid":290158.74,"grandTotalActual":337729.86,"variance":47571.12,"variancePct":16.39},{"event_name":"Jeep VIP Experience","client":"Jeep","lead_office":"Chicago","grandTotalBid":343383.1,"grandTotalActual":296025.36,"variance":-47357.74,"variancePct":-13.79},{"event_name":"Mercedes-Benz Auto Show 2025","client":"Mercedes-Benz","lead_office":"Dallas","grandTotalBid":299798.18,"grandTotalActual":252508.5,"variance":-47289.68,"variancePct":-15.77},{"event_name":"Subaru Regional Tour","client":"Subaru","lead_office":"San Francisco","grandTotalBid":197202.15,"grandTotalActual":150163.11,"variance":-47039.04,"variancePct":-23.85},{"event_name":"Ram Auto Show 2018","client":"Ram","lead_office":"San Francisco","grandTotalBid":343104.13,"grandTotalActual":390080.05,"variance":46975.92,"variancePct":13.69},{"event_name":"Dodge Launch Event","client":"Dodge","lead_office":"Miami","grandTotalBid":298390.32,"grandTotalActual":251991.29,"variance":-46399.03,"variancePct":-15.55},{"event_name":"Land Rover Regional Tour","client":"Land Rover","lead_office":"Portland","grandTotalBid":241915.52,"grandTotalActual":287927.92,"variance":46012.4,"variancePct":19.02},{"event_name":"Ford Drive Experience","client":"Ford","lead_office":"Miami","grandTotalBid":158690.23,"grandTotalActual":204130.12,"variance":45439.89,"variancePct":28.63},{"event_name":"Lucid Drive Experience","client":"Lucid","lead_office":"Nashville","grandTotalBid":129415.89,"grandTotalActual":174854.64,"variance":45438.75,"variancePct":35.11},{"event_name":"Dodge Brand Activation","client":"Dodge","lead_office":"Seattle","grandTotalBid":202811.62,"grandTotalActual":248033.43,"variance":45221.81,"variancePct":22.3},{"event_name":"Audi Auto Show 2023","client":"Audi","lead_office":"Atlanta","grandTotalBid":230731.77,"grandTotalActual":275845.39,"variance":45113.62,"variancePct":19.55},{"event_name":"Chrysler Dealer Meeting","client":"Chrysler","lead_office":"Miami","grandTotalBid":348781.33,"grandTotalActual":393336.31,"variance":44554.98,"variancePct":12.77},{"event_name":"Mercedes-Benz Dealer Meeting","client":"Mercedes-Benz","lead_office":"Seattle","grandTotalBid":253272.13,"grandTotalActual":297819.02,"variance":44546.89,"variancePct":17.59},{"event_name":"Hyundai VIP Experience","client":"Hyundai","lead_office":"Los Angeles","grandTotalBid":255504.56,"grandTotalActual":299961.7,"variance":44457.14,"variancePct":17.4},{"event_name":"Nissan Regional Tour","client":"Nissan","lead_office":"Dallas","grandTotalBid":272170.52,"grandTotalActual":316435.47,"variance":44264.95,"variancePct":16.26},{"event_name":"Subaru VIP Experience","client":"Subaru","lead_office":"Atlanta","grandTotalBid":221431.97,"grandTotalActual":265609.42,"variance":44177.45,"variancePct":19.95},{"event_name":"Lexus Auto Show 2025","client":"Lexus","lead_office":"Dallas","grandTotalBid":324616.93,"grandTotalActual":368704.55,"variance":44087.62,"variancePct":13.58}]}